soremoji/__init__.py
soremoji/__main__.py
soremoji/cli.py
soremoji/command.py
soremoji/emoticon.py
soremoji/feature.py
soremoji-0.3.4.dist-info/LICENSE
soremoji-0.3.4.dist-info/METADATA
soremoji-0.3.4.dist-info/WHEEL
soremoji-0.3.4.dist-info/entry_points.txt
soremoji-0.3.4.dist-info/RECORD
