Metadata-Version: 2.1
Name: soremoji
Version: 0.3.4
Summary: 自维护的 gitmoji-cli，做了部分更改
License: MIT
Author: mute.
Author-email: mute231010@gmail.com
Requires-Python: >=3.10,<4.0
Classifier: License :: OSI Approved :: MIT License
Classifier: Programming Language :: Python :: 3
Classifier: Programming Language :: Python :: 3.10
Classifier: Programming Language :: Python :: 3.11
Requires-Dist: sorampt (>=0.1.6,<0.2.0)
Requires-Dist: wcwidth (>=0.2.6,<0.3.0)
